img2fmri/__init__.py
img2fmri/predict.py
img2fmri/utils.py
img2fmri/derivatives/init_brain.nii.gz
img2fmri/derivatives/shape_array.npy
img2fmri/derivatives/T1/sub-CSI1_ses-16_anat_sub-CSI1_ses-16_T1w.nii.gz
img2fmri/derivatives/T1/sub-CSI2_ses-16_anat_sub-CSI2_ses-16_T1w.nii.gz
img2fmri/derivatives/T1/sub-CSI3_ses-16_anat_sub-CSI3_ses-16_T1w.nii.gz
img2fmri/derivatives/bool_masks/derivatives_spm_sub-CSI1_sub-CSI1_mask-LHEarlyVis.nii.gz
img2fmri/derivatives/bool_masks/derivatives_spm_sub-CSI1_sub-CSI1_mask-LHLOC.nii.gz
img2fmri/derivatives/bool_masks/derivatives_spm_sub-CSI1_sub-CSI1_mask-LHOPA.nii.gz
img2fmri/derivatives/bool_masks/derivatives_spm_sub-CSI1_sub-CSI1_mask-LHPPA.nii.gz
img2fmri/derivatives/bool_masks/derivatives_spm_sub-CSI1_sub-CSI1_mask-LHRSC.nii.gz
img2fmri/derivatives/bool_masks/derivatives_spm_sub-CSI1_sub-CSI1_mask-RHEarlyVis.nii.gz
img2fmri/derivatives/bool_masks/derivatives_spm_sub-CSI1_sub-CSI1_mask-RHLOC.nii.gz
img2fmri/derivatives/bool_masks/derivatives_spm_sub-CSI1_sub-CSI1_mask-RHOPA.nii.gz
img2fmri/derivatives/bool_masks/derivatives_spm_sub-CSI1_sub-CSI1_mask-RHPPA.nii.gz
img2fmri/derivatives/bool_masks/derivatives_spm_sub-CSI1_sub-CSI1_mask-RHRSC.nii.gz
img2fmri/derivatives/bool_masks/derivatives_spm_sub-CSI2_sub-CSI2_mask-LHEarlyVis.nii.gz
img2fmri/derivatives/bool_masks/derivatives_spm_sub-CSI2_sub-CSI2_mask-LHLOC.nii.gz
img2fmri/derivatives/bool_masks/derivatives_spm_sub-CSI2_sub-CSI2_mask-LHOPA.nii.gz
img2fmri/derivatives/bool_masks/derivatives_spm_sub-CSI2_sub-CSI2_mask-LHPPA.nii.gz
img2fmri/derivatives/bool_masks/derivatives_spm_sub-CSI2_sub-CSI2_mask-LHRSC.nii.gz
img2fmri/derivatives/bool_masks/derivatives_spm_sub-CSI2_sub-CSI2_mask-RHEarlyVis.nii.gz
img2fmri/derivatives/bool_masks/derivatives_spm_sub-CSI2_sub-CSI2_mask-RHLOC.nii.gz
img2fmri/derivatives/bool_masks/derivatives_spm_sub-CSI2_sub-CSI2_mask-RHOPA.nii.gz
img2fmri/derivatives/bool_masks/derivatives_spm_sub-CSI2_sub-CSI2_mask-RHPPA.nii.gz
img2fmri-1.0.dist-info/LICENSE.txt
img2fmri-1.0.dist-info/METADATA
img2fmri-1.0.dist-info/WHEEL
img2fmri-1.0.dist-info/entry_points.txt
img2fmri-1.0.dist-info/top_level.txt
img2fmri-1.0.dist-info/RECORD
