Metadata-Version: 2.1
Name: img2fmri
Version: 1.0
Summary: img2fmri: a python package for predicting group-level fMRI responses to visual stimuli using deep neural networks
Author-email: Max Bennett <mbb2176@columbia.edu>
Project-URL: Homepage, https://github.com/dpmlab/img2fmri
Project-URL: Bug Tracker, https://github.com/dpmlab/img2fmri/issues
Classifier: Programming Language :: Python :: 3
Classifier: License :: OSI Approved :: MIT License
Classifier: Operating System :: OS Independent
Requires-Python: >=3.9
License-File: LICENSE.txt
Requires-Dist: nibabel (>=5.1.0)
Requires-Dist: nipype (>=1.8)
Requires-Dist: numpy (>=1.25.1)
Requires-Dist: joblib (>=1)
Requires-Dist: natsort (>=8.4.0)
Requires-Dist: opencv-python (>=4)
Requires-Dist: Pillow (>=10)
Requires-Dist: scikit-learn (>=1.3.0)
Requires-Dist: scipy (>=1.11.1)
Requires-Dist: torch (>=2.0.1)
Requires-Dist: torchvision (>=0.15.2)
Requires-Dist: tqdm (>=4.65.0)
Requires-Dist: pytest (>=7.1)
Requires-Dist: wget (>=3.2)
